syft_flwr/__init__.py
syft_flwr/bootstrap.py
syft_flwr/cli.py
syft_flwr/config.py
syft_flwr/consts.py
syft_flwr/gdrive_io.py
syft_flwr/mounts.py
syft_flwr/run.py
syft_flwr/run_simulation.py
syft_flwr/serde.py
syft_flwr/utils.py
syft_flwr/client/__init__.py
syft_flwr/client/factory.py
syft_flwr/client/protocol.py
syft_flwr/client/syft_core_client.py
syft_flwr/client/syft_p2p_client.py
syft_flwr/events/__init__.py
syft_flwr/events/factory.py
syft_flwr/events/p2p_fle_events.py
syft_flwr/events/protocol.py
syft_flwr/events/syft_events.py
syft_flwr/fl_orchestrator/__init__.py
syft_flwr/fl_orchestrator/flower_client.py
syft_flwr/fl_orchestrator/flower_server.py
syft_flwr/fl_orchestrator/syft_grid.py
syft_flwr/rpc/__init__.py
syft_flwr/rpc/factory.py
syft_flwr/rpc/p2p_file_rpc.py
syft_flwr/rpc/protocol.py
syft_flwr/rpc/syft_rpc.py
syft_flwr/strategy/__init__.py
syft_flwr/strategy/fedavg.py
syft_flwr/templates/main.py.tpl
syft_flwr-0.5.0.dist-info/METADATA
syft_flwr-0.5.0.dist-info/WHEEL
syft_flwr-0.5.0.dist-info/entry_points.txt
syft_flwr-0.5.0.dist-info/licenses/LICENSE
syft_flwr-0.5.0.dist-info/RECORD
