Metadata-Version: 2.4
Name: syft-flwr
Version: 0.5.0
Summary: syft_flwr is an open source framework that facilitate federated learning projects using Flower over the SyftBox protocol
License-File: LICENSE
Requires-Python: <3.14,>=3.12
Requires-Dist: flwr-datasets[vision]>=0.5.0
Requires-Dist: flwr[simulation]==1.25.0
Requires-Dist: huggingface-hub>=0.26.0
Requires-Dist: loguru>=0.7.3
Requires-Dist: safetensors>=0.7.0
Requires-Dist: syft-client>=0.1.94
Requires-Dist: syft-dataset>=0.1.5
Requires-Dist: syft-job>=0.1.23
Requires-Dist: syft-rds>=0.5.0
Requires-Dist: tomli-w>=1.2.0
Requires-Dist: tomli>=2.3.0
Requires-Dist: typing-extensions>=4.13.0
